{"parts":[{"names":["window_ext"],"positionDefinitions":["7a1adbe6"],"condition":"NORMAL","renderStage":"EXTERIOR","type":"NORMAL","displayXPadding":0.0,"displayYPadding":0.0,"displayColorCjk":"FF9900","displayColor":"FF9900","displayMaxLineHeight":1.5,"displayCjkSizeRatio":2.0,"displayOptions":[],"displayPadZeros":0.0,"displayType":"DESTINATION","displayDefaultText":"Ñäk Ħñisòh","doorXMultiplier":0.0,"doorZMultiplier":0.0,"doorAnimationType":"STANDARD","renderFromOpeningDoorTime":0,"renderUntilOpeningDoorTime":0,"renderFromClosingDoorTime":0,"renderUntilClosingDoorTime":0,"flashOffTime":0,"flashOnTime":0},{"names":["window_int"],"positionDefinitions":["c679967"],"condition":"NORMAL","renderStage":"INTERIOR","type":"NORMAL","displayXPadding":0.0,"displayYPadding":0.0,"displayColorCjk":"FF9900","displayColor":"FF9900","displayMaxLineHeight":1.5,"displayCjkSizeRatio":2.0,"displayOptions":[],"displayPadZeros":0.0,"displayType":"DESTINATION","displayDefaultText":"Ñäk Ħñisòh","doorXMultiplier":0.0,"doorZMultiplier":0.0,"doorAnimationType":"STANDARD","renderFromOpeningDoorTime":0,"renderUntilOpeningDoorTime":0,"renderFromClosingDoorTime":0,"renderUntilClosingDoorTime":0,"flashOffTime":0,"flashOnTime":0},{"names":["window_floor"],"positionDefinitions":["24a20cfd"],"condition":"NORMAL","renderStage":"EXTERIOR","type":"FLOOR","displayXPadding":0.0,"displayYPadding":0.0,"displayColorCjk":"FF9900","displayColor":"FF9900","displayMaxLineHeight":1.5,"displayCjkSizeRatio":2.0,"displayOptions":[],"displayPadZeros":0.0,"displayType":"DESTINATION","displayDefaultText":"Ñäk Ħñisòh","doorXMultiplier":0.0,"doorZMultiplier":0.0,"doorAnimationType":"STANDARD","renderFromOpeningDoorTime":0,"renderUntilOpeningDoorTime":0,"renderFromClosingDoorTime":0,"renderUntilClosingDoorTime":0,"flashOffTime":0,"flashOnTime":0},{"names":["door_ext"],"positionDefinitions":["3a6d32c0"],"condition":"NORMAL","renderStage":"EXTERIOR","type":"NORMAL","displayXPadding":0.0,"displayYPadding":0.0,"displayColorCjk":"FF9900","displayColor":"FF9900","displayMaxLineHeight":1.5,"displayCjkSizeRatio":2.0,"displayOptions":[],"displayPadZeros":0.0,"displayType":"DESTINATION","displayDefaultText":"Ñäk Ħñisòh","doorXMultiplier":0.0,"doorZMultiplier":0.0,"doorAnimationType":"STANDARD","renderFromOpeningDoorTime":0,"renderUntilOpeningDoorTime":0,"renderFromClosingDoorTime":0,"renderUntilClosingDoorTime":0,"flashOffTime":0,"flashOnTime":0},{"names":["door_int"],"positionDefinitions":["a3a9edd6"],"condition":"NORMAL","renderStage":"INTERIOR","type":"NORMAL","displayXPadding":0.0,"displayYPadding":0.0,"displayColorCjk":"FF9900","displayColor":"FF9900","displayMaxLineHeight":1.5,"displayCjkSizeRatio":2.0,"displayOptions":[],"displayPadZeros":0.0,"displayType":"DESTINATION","displayDefaultText":"Ñäk Ħñisòh","doorXMultiplier":0.0,"doorZMultiplier":0.0,"doorAnimationType":"STANDARD","renderFromOpeningDoorTime":0,"renderUntilOpeningDoorTime":0,"renderFromClosingDoorTime":0,"renderUntilClosingDoorTime":0,"flashOffTime":0,"flashOnTime":0},{"names":["door_floor"],"positionDefinitions":["45a19547"],"condition":"NORMAL","renderStage":"EXTERIOR","type":"FLOOR","displayXPadding":0.0,"displayYPadding":0.0,"displayColorCjk":"FF9900","displayColor":"FF9900","displayMaxLineHeight":1.5,"displayCjkSizeRatio":2.0,"displayOptions":[],"displayPadZeros":0.0,"displayType":"DESTINATION","displayDefaultText":"Ñäk Ħñisòh","doorXMultiplier":0.0,"doorZMultiplier":0.0,"doorAnimationType":"STANDARD","renderFromOpeningDoorTime":0,"renderUntilOpeningDoorTime":0,"renderFromClosingDoorTime":0,"renderUntilClosingDoorTime":0,"flashOffTime":0,"flashOnTime":0},{"names":["doorway"],"positionDefinitions":["bc8ae2f1"],"condition":"NORMAL","renderStage":"EXTERIOR","type":"DOORWAY","displayXPadding":0.0,"displayYPadding":0.0,"displayColorCjk":"FF9900","displayColor":"FF9900","displayMaxLineHeight":1.5,"displayCjkSizeRatio":2.0,"displayOptions":[],"displayPadZeros":0.0,"displayType":"DESTINATION","displayDefaultText":"Ñäk Ħñisòh","doorXMultiplier":0.0,"doorZMultiplier":0.0,"doorAnimationType":"STANDARD","renderFromOpeningDoorTime":0,"renderUntilOpeningDoorTime":0,"renderFromClosingDoorTime":0,"renderUntilClosingDoorTime":0,"flashOffTime":0,"flashOnTime":0},{"names":["door_display_base"],"positionDefinitions":["98dc0ad4"],"condition":"DOORS_CLOSED","renderStage":"ALWAYS_ON_LIGHT","type":"NORMAL","displayXPadding":0.0,"displayYPadding":0.0,"displayColorCjk":"FF9900","displayColor":"FF9900","displayMaxLineHeight":1.5,"displayCjkSizeRatio":2.0,"displayOptions":[],"displayPadZeros":0.0,"displayType":"DESTINATION","displayDefaultText":"Ñäk Ħñisòh","doorXMultiplier":0.0,"doorZMultiplier":0.0,"doorAnimationType":"STANDARD","renderFromOpeningDoorTime":0,"renderUntilOpeningDoorTime":0,"renderFromClosingDoorTime":0,"renderUntilClosingDoorTime":0,"flashOffTime":0,"flashOnTime":0},{"names":["door_display_ns"],"positionDefinitions":["fabda83a"],"condition":"DOORS_CLOSED","renderStage":"EXTERIOR","type":"DISPLAY","displayXPadding":0.0,"displayYPadding":0.0,"displayColorCjk":"000000","displayColor":"000000","displayMaxLineHeight":1.5,"displayCjkSizeRatio":2.0,"displayOptions":["SCROLL_NORMAL"],"displayPadZeros":0.0,"displayType":"NEXT_STATION","displayDefaultText":"","doorXMultiplier":0.0,"doorZMultiplier":0.0,"doorAnimationType":"STANDARD","renderFromOpeningDoorTime":0,"renderUntilOpeningDoorTime":0,"renderFromClosingDoorTime":0,"renderUntilClosingDoorTime":0,"flashOffTime":0,"flashOnTime":0},{"names":["door_display_dest"],"positionDefinitions":["868ba1d4"],"condition":"DOORS_CLOSED","renderStage":"EXTERIOR","type":"DISPLAY","displayXPadding":0.0,"displayYPadding":0.0,"displayColorCjk":"000000","displayColor":"000000","displayMaxLineHeight":1.5,"displayCjkSizeRatio":2.0,"displayOptions":["SCROLL_NORMAL"],"displayPadZeros":0.0,"displayType":"DESTINATION","displayDefaultText":"","doorXMultiplier":0.0,"doorZMultiplier":0.0,"doorAnimationType":"STANDARD","renderFromOpeningDoorTime":0,"renderUntilOpeningDoorTime":0,"renderFromClosingDoorTime":0,"renderUntilClosingDoorTime":0,"flashOffTime":0,"flashOnTime":0},{"names":["door_display_info"],"positionDefinitions":["a7068e5b"],"condition":"DOORS_CLOSED","renderStage":"EXTERIOR","type":"DISPLAY","displayXPadding":0.0,"displayYPadding":0.125,"displayColorCjk":"FFFFFF","displayColor":"FFFFFF","displayMaxLineHeight":1.75,"displayCjkSizeRatio":2.0,"displayOptions":["SCROLL_NORMAL"],"displayPadZeros":0.0,"displayType":"NEXT_STATION_UK","displayDefaultText":"Geen Dienst","doorXMultiplier":0.0,"doorZMultiplier":0.0,"doorAnimationType":"STANDARD","renderFromOpeningDoorTime":0,"renderUntilOpeningDoorTime":0,"renderFromClosingDoorTime":0,"renderUntilClosingDoorTime":0,"flashOffTime":0,"flashOnTime":0},{"names":["door_display_plat"],"positionDefinitions":["76bca31a"],"condition":"DOORS_OPENED","renderStage":"ALWAYS_ON_LIGHT","type":"NORMAL","displayXPadding":0.0,"displayYPadding":0.0,"displayColorCjk":"FF9900","displayColor":"FF9900","displayMaxLineHeight":1.5,"displayCjkSizeRatio":2.0,"displayOptions":[],"displayPadZeros":0.0,"displayType":"DESTINATION","displayDefaultText":"Ñäk Ħñisòh","doorXMultiplier":0.0,"doorZMultiplier":0.0,"doorAnimationType":"STANDARD","renderFromOpeningDoorTime":0,"renderUntilOpeningDoorTime":0,"renderFromClosingDoorTime":0,"renderUntilClosingDoorTime":0,"flashOffTime":0,"flashOnTime":0},{"names":["door_display_plat_station"],"positionDefinitions":["85908789"],"condition":"DOORS_OPENED","renderStage":"EXTERIOR","type":"DISPLAY","displayXPadding":0.0,"displayYPadding":0.0,"displayColorCjk":"000000","displayColor":"000000","displayMaxLineHeight":1.5,"displayCjkSizeRatio":2.0,"displayOptions":[],"displayPadZeros":0.0,"displayType":"NEXT_STATION","displayDefaultText":"Geen Dienst","doorXMultiplier":0.0,"doorZMultiplier":0.0,"doorAnimationType":"STANDARD","renderFromOpeningDoorTime":0,"renderUntilOpeningDoorTime":0,"renderFromClosingDoorTime":0,"renderUntilClosingDoorTime":0,"flashOffTime":0,"flashOnTime":0},{"names":["door_left_ext"],"positionDefinitions":["58a1cd63"],"condition":"NORMAL","renderStage":"EXTERIOR","type":"NORMAL","displayXPadding":0.0,"displayYPadding":0.0,"displayColorCjk":"FF9900","displayColor":"FF9900","displayMaxLineHeight":1.5,"displayCjkSizeRatio":2.0,"displayOptions":[],"displayPadZeros":0.0,"displayType":"DESTINATION","displayDefaultText":"Ñäk Ħñisòh","doorXMultiplier":-1.0,"doorZMultiplier":12.0,"doorAnimationType":"PLUG_FAST","renderFromOpeningDoorTime":0,"renderUntilOpeningDoorTime":0,"renderFromClosingDoorTime":0,"renderUntilClosingDoorTime":0,"flashOffTime":0,"flashOnTime":0},{"names":["door_right_ext"],"positionDefinitions":["94a63a4f"],"condition":"NORMAL","renderStage":"EXTERIOR","type":"NORMAL","displayXPadding":0.0,"displayYPadding":0.0,"displayColorCjk":"FF9900","displayColor":"FF9900","displayMaxLineHeight":1.5,"displayCjkSizeRatio":2.0,"displayOptions":[],"displayPadZeros":0.0,"displayType":"DESTINATION","displayDefaultText":"Ñäk Ħñisòh","doorXMultiplier":-1.0,"doorZMultiplier":-12.0,"doorAnimationType":"PLUG_FAST","renderFromOpeningDoorTime":0,"renderUntilOpeningDoorTime":0,"renderFromClosingDoorTime":0,"renderUntilClosingDoorTime":0,"flashOffTime":0,"flashOnTime":0},{"names":["door_left_alarm"],"positionDefinitions":["e1d1b3d6"],"condition":"DOORS_OPENED","renderStage":"ALWAYS_ON_LIGHT","type":"NORMAL","displayXPadding":0.0,"displayYPadding":0.0,"displayColorCjk":"FF9900","displayColor":"FF9900","displayMaxLineHeight":1.5,"displayCjkSizeRatio":2.0,"displayOptions":[],"displayPadZeros":0.0,"displayType":"DESTINATION","displayDefaultText":"Ñäk Ħñisòh","doorXMultiplier":-1.0,"doorZMultiplier":12.0,"doorAnimationType":"PLUG_FAST","renderFromOpeningDoorTime":100,"renderUntilOpeningDoorTime":1999,"renderFromClosingDoorTime":1999,"renderUntilClosingDoorTime":100,"flashOffTime":250,"flashOnTime":250},{"names":["door_right_alarm"],"positionDefinitions":["269360f3"],"condition":"DOORS_OPENED","renderStage":"ALWAYS_ON_LIGHT","type":"NORMAL","displayXPadding":0.0,"displayYPadding":0.0,"displayColorCjk":"FF9900","displayColor":"FF9900","displayMaxLineHeight":1.5,"displayCjkSizeRatio":2.0,"displayOptions":[],"displayPadZeros":0.0,"displayType":"DESTINATION","displayDefaultText":"Ñäk Ħñisòh","doorXMultiplier":-1.0,"doorZMultiplier":-12.0,"doorAnimationType":"PLUG_FAST","renderFromOpeningDoorTime":100,"renderUntilOpeningDoorTime":1999,"renderFromClosingDoorTime":1999,"renderUntilClosingDoorTime":100,"flashOffTime":250,"flashOnTime":250},{"names":["door_left_alarm"],"positionDefinitions":["7050c3bc"],"condition":"DOORS_OPENED","renderStage":"ALWAYS_ON_LIGHT","type":"NORMAL","displayXPadding":0.0,"displayYPadding":0.0,"displayColorCjk":"FF9900","displayColor":"FF9900","displayMaxLineHeight":1.5,"displayCjkSizeRatio":2.0,"displayOptions":[],"displayPadZeros":0.0,"displayType":"DESTINATION","displayDefaultText":"Ñäk Ħñisòh","doorXMultiplier":-1.0,"doorZMultiplier":12.0,"doorAnimationType":"PLUG_FAST","renderFromOpeningDoorTime":2000,"renderUntilOpeningDoorTime":5000,"renderFromClosingDoorTime":5000,"renderUntilClosingDoorTime":2000,"flashOffTime":0,"flashOnTime":0},{"names":["door_right_alarm"],"positionDefinitions":["d18125ea"],"condition":"DOORS_OPENED","renderStage":"ALWAYS_ON_LIGHT","type":"NORMAL","displayXPadding":0.0,"displayYPadding":0.0,"displayColorCjk":"FF9900","displayColor":"FF9900","displayMaxLineHeight":1.5,"displayCjkSizeRatio":2.0,"displayOptions":[],"displayPadZeros":0.0,"displayType":"DESTINATION","displayDefaultText":"Ñäk Ħñisòh","doorXMultiplier":-1.0,"doorZMultiplier":-12.0,"doorAnimationType":"PLUG_FAST","renderFromOpeningDoorTime":2000,"renderUntilOpeningDoorTime":5000,"renderFromClosingDoorTime":5000,"renderUntilClosingDoorTime":2000,"flashOffTime":0,"flashOnTime":0},{"names":["door_left_int"],"positionDefinitions":["f126fdec"],"condition":"NORMAL","renderStage":"INTERIOR","type":"NORMAL","displayXPadding":0.0,"displayYPadding":0.0,"displayColorCjk":"FF9900","displayColor":"FF9900","displayMaxLineHeight":1.5,"displayCjkSizeRatio":2.0,"displayOptions":[],"displayPadZeros":0.0,"displayType":"DESTINATION","displayDefaultText":"Ñäk Ħñisòh","doorXMultiplier":-1.0,"doorZMultiplier":12.0,"doorAnimationType":"PLUG_FAST","renderFromOpeningDoorTime":0,"renderUntilOpeningDoorTime":0,"renderFromClosingDoorTime":0,"renderUntilClosingDoorTime":0,"flashOffTime":0,"flashOnTime":0},{"names":["door_right_int"],"positionDefinitions":["58d4191e"],"condition":"NORMAL","renderStage":"INTERIOR","type":"NORMAL","displayXPadding":0.0,"displayYPadding":0.0,"displayColorCjk":"FF9900","displayColor":"FF9900","displayMaxLineHeight":1.5,"displayCjkSizeRatio":2.0,"displayOptions":[],"displayPadZeros":0.0,"displayType":"DESTINATION","displayDefaultText":"Ñäk Ħñisòh","doorXMultiplier":-1.0,"doorZMultiplier":-12.0,"doorAnimationType":"PLUG_FAST","renderFromOpeningDoorTime":0,"renderUntilOpeningDoorTime":0,"renderFromClosingDoorTime":0,"renderUntilClosingDoorTime":0,"flashOffTime":0,"flashOnTime":0},{"names":["end_ext"],"positionDefinitions":["f31d1906"],"condition":"NORMAL","renderStage":"EXTERIOR","type":"NORMAL","displayXPadding":0.0,"displayYPadding":0.0,"displayColorCjk":"FF9900","displayColor":"FF9900","displayMaxLineHeight":1.5,"displayCjkSizeRatio":2.0,"displayOptions":[],"displayPadZeros":0.0,"displayType":"DESTINATION","displayDefaultText":"Ñäk Ħñisòh","doorXMultiplier":0.0,"doorZMultiplier":0.0,"doorAnimationType":"STANDARD","renderFromOpeningDoorTime":0,"renderUntilOpeningDoorTime":0,"renderFromClosingDoorTime":0,"renderUntilClosingDoorTime":0,"flashOffTime":0,"flashOnTime":0},{"names":["end_int"],"positionDefinitions":["6d08feb1"],"condition":"NORMAL","renderStage":"INTERIOR","type":"NORMAL","displayXPadding":0.0,"displayYPadding":0.0,"displayColorCjk":"FF9900","displayColor":"FF9900","displayMaxLineHeight":1.5,"displayCjkSizeRatio":2.0,"displayOptions":[],"displayPadZeros":0.0,"displayType":"DESTINATION","displayDefaultText":"Ñäk Ħñisòh","doorXMultiplier":0.0,"doorZMultiplier":0.0,"doorAnimationType":"STANDARD","renderFromOpeningDoorTime":0,"renderUntilOpeningDoorTime":0,"renderFromClosingDoorTime":0,"renderUntilClosingDoorTime":0,"flashOffTime":0,"flashOnTime":0},{"names":["end_floor"],"positionDefinitions":["d0f8e91c"],"condition":"NORMAL","renderStage":"EXTERIOR","type":"FLOOR","displayXPadding":0.0,"displayYPadding":0.0,"displayColorCjk":"FF9900","displayColor":"FF9900","displayMaxLineHeight":1.5,"displayCjkSizeRatio":2.0,"displayOptions":[],"displayPadZeros":0.0,"displayType":"DESTINATION","displayDefaultText":"Ñäk Ħñisòh","doorXMultiplier":0.0,"doorZMultiplier":0.0,"doorAnimationType":"STANDARD","renderFromOpeningDoorTime":0,"renderUntilOpeningDoorTime":0,"renderFromClosingDoorTime":0,"renderUntilClosingDoorTime":0,"flashOffTime":0,"flashOnTime":0},{"names":["end_door_transparent"],"positionDefinitions":["6cd3084b"],"condition":"NORMAL","renderStage":"INTERIOR_TRANSLUCENT","type":"NORMAL","displayXPadding":0.0,"displayYPadding":0.0,"displayColorCjk":"FF9900","displayColor":"FF9900","displayMaxLineHeight":1.5,"displayCjkSizeRatio":2.0,"displayOptions":[],"displayPadZeros":0.0,"displayType":"DESTINATION","displayDefaultText":"Ñäk Ħñisòh","doorXMultiplier":0.0,"doorZMultiplier":0.0,"doorAnimationType":"STANDARD","renderFromOpeningDoorTime":0,"renderUntilOpeningDoorTime":0,"renderFromClosingDoorTime":0,"renderUntilClosingDoorTime":0,"flashOffTime":0,"flashOnTime":0},{"names":["side_ad"],"positionDefinitions":["abaa72e2"],"condition":"NORMAL","renderStage":"EXTERIOR","type":"NORMAL","displayXPadding":0.0,"displayYPadding":0.0,"displayColorCjk":"FF9900","displayColor":"FF9900","displayMaxLineHeight":1.5,"displayCjkSizeRatio":2.0,"displayOptions":[],"displayPadZeros":0.0,"displayType":"DESTINATION","displayDefaultText":"Ñäk Ħñisòh","doorXMultiplier":0.0,"doorZMultiplier":0.0,"doorAnimationType":"STANDARD","renderFromOpeningDoorTime":0,"renderUntilOpeningDoorTime":0,"renderFromClosingDoorTime":0,"renderUntilClosingDoorTime":0,"flashOffTime":0,"flashOnTime":0},{"names":["seat"],"positionDefinitions":["1c146beb"],"condition":"NORMAL","renderStage":"EXTERIOR","type":"NORMAL","displayXPadding":0.0,"displayYPadding":0.0,"displayColorCjk":"FF9900","displayColor":"FF9900","displayMaxLineHeight":1.5,"displayCjkSizeRatio":2.0,"displayOptions":[],"displayPadZeros":0.0,"displayType":"DESTINATION","displayDefaultText":"Ñäk Ħñisòh","doorXMultiplier":0.0,"doorZMultiplier":0.0,"doorAnimationType":"STANDARD","renderFromOpeningDoorTime":0,"renderUntilOpeningDoorTime":0,"renderFromClosingDoorTime":0,"renderUntilClosingDoorTime":0,"flashOffTime":0,"flashOnTime":0},{"names":["seat"],"positionDefinitions":["c94270df"],"condition":"NORMAL","renderStage":"EXTERIOR","type":"SEAT","displayXPadding":0.0,"displayYPadding":0.0,"displayColorCjk":"FF9900","displayColor":"FF9900","displayMaxLineHeight":1.5,"displayCjkSizeRatio":2.0,"displayOptions":[],"displayPadZeros":0.0,"displayType":"DESTINATION","displayDefaultText":"Ñäk Ħñisòh","doorXMultiplier":0.0,"doorZMultiplier":0.0,"doorAnimationType":"STANDARD","renderFromOpeningDoorTime":0,"renderUntilOpeningDoorTime":0,"renderFromClosingDoorTime":0,"renderUntilClosingDoorTime":0,"flashOffTime":0,"flashOnTime":0},{"names":["head_ext"],"positionDefinitions":["5a27b8a0"],"condition":"NORMAL","renderStage":"EXTERIOR","type":"NORMAL","displayXPadding":0.0,"displayYPadding":0.0,"displayColorCjk":"FF9900","displayColor":"FF9900","displayMaxLineHeight":1.5,"displayCjkSizeRatio":2.0,"displayOptions":[],"displayPadZeros":0.0,"displayType":"DESTINATION","displayDefaultText":"Ñäk Ħñisòh","doorXMultiplier":0.0,"doorZMultiplier":0.0,"doorAnimationType":"STANDARD","renderFromOpeningDoorTime":0,"renderUntilOpeningDoorTime":0,"renderFromClosingDoorTime":0,"renderUntilClosingDoorTime":0,"flashOffTime":0,"flashOnTime":0},{"names":["head_int"],"positionDefinitions":["f18fe729"],"condition":"NORMAL","renderStage":"INTERIOR","type":"NORMAL","displayXPadding":0.0,"displayYPadding":0.0,"displayColorCjk":"FF9900","displayColor":"FF9900","displayMaxLineHeight":1.5,"displayCjkSizeRatio":2.0,"displayOptions":[],"displayPadZeros":0.0,"displayType":"DESTINATION","displayDefaultText":"Ñäk Ħñisòh","doorXMultiplier":0.0,"doorZMultiplier":0.0,"doorAnimationType":"STANDARD","renderFromOpeningDoorTime":0,"renderUntilOpeningDoorTime":0,"renderFromClosingDoorTime":0,"renderUntilClosingDoorTime":0,"flashOffTime":0,"flashOnTime":0},{"names":["head_floor"],"positionDefinitions":["2cdb404d"],"condition":"NORMAL","renderStage":"EXTERIOR","type":"FLOOR","displayXPadding":0.0,"displayYPadding":0.0,"displayColorCjk":"FF9900","displayColor":"FF9900","displayMaxLineHeight":1.5,"displayCjkSizeRatio":2.0,"displayOptions":[],"displayPadZeros":0.0,"displayType":"DESTINATION","displayDefaultText":"Ñäk Ħñisòh","doorXMultiplier":0.0,"doorZMultiplier":0.0,"doorAnimationType":"STANDARD","renderFromOpeningDoorTime":0,"renderUntilOpeningDoorTime":0,"renderFromClosingDoorTime":0,"renderUntilClosingDoorTime":0,"flashOffTime":0,"flashOnTime":0},{"names":["headlights"],"positionDefinitions":["462b51b0"],"condition":"ON_ROUTE_FORWARDS","renderStage":"ALWAYS_ON_LIGHT","type":"NORMAL","displayXPadding":0.0,"displayYPadding":0.0,"displayColorCjk":"FF9900","displayColor":"FF9900","displayMaxLineHeight":1.5,"displayCjkSizeRatio":2.0,"displayOptions":[],"displayPadZeros":0.0,"displayType":"DESTINATION","displayDefaultText":"Ñäk Ħñisòh","doorXMultiplier":0.0,"doorZMultiplier":0.0,"doorAnimationType":"STANDARD","renderFromOpeningDoorTime":0,"renderUntilOpeningDoorTime":0,"renderFromClosingDoorTime":0,"renderUntilClosingDoorTime":0,"flashOffTime":0,"flashOnTime":0},{"names":["taillights"],"positionDefinitions":["e064b56f"],"condition":"ON_ROUTE_BACKWARDS","renderStage":"ALWAYS_ON_LIGHT","type":"NORMAL","displayXPadding":0.0,"displayYPadding":0.0,"displayColorCjk":"FF9900","displayColor":"FF9900","displayMaxLineHeight":1.5,"displayCjkSizeRatio":2.0,"displayOptions":[],"displayPadZeros":0.0,"displayType":"DESTINATION","displayDefaultText":"Ñäk Ħñisòh","doorXMultiplier":0.0,"doorZMultiplier":0.0,"doorAnimationType":"STANDARD","renderFromOpeningDoorTime":0,"renderUntilOpeningDoorTime":0,"renderFromClosingDoorTime":0,"renderUntilClosingDoorTime":0,"flashOffTime":0,"flashOnTime":0},{"names":["head_destination"],"positionDefinitions":["6a887cc"],"condition":"NORMAL","renderStage":"EXTERIOR","type":"DISPLAY","displayXPadding":0.0,"displayYPadding":0.0,"displayColorCjk":"FFFFFF","displayColor":"FFFFFF","displayMaxLineHeight":1.5,"displayCjkSizeRatio":2.0,"displayOptions":[],"displayPadZeros":0.0,"displayType":"DESTINATION","displayDefaultText":"Geen Dienst","doorXMultiplier":0.0,"doorZMultiplier":0.0,"doorAnimationType":"STANDARD","renderFromOpeningDoorTime":0,"renderUntilOpeningDoorTime":0,"renderFromClosingDoorTime":0,"renderUntilClosingDoorTime":0,"flashOffTime":0,"flashOnTime":0},{"names":["head_color"],"positionDefinitions":["c067dc55"],"condition":"NORMAL","renderStage":"EXTERIOR","type":"DISPLAY","displayXPadding":0.0,"displayYPadding":0.0,"displayColorCjk":"FF9900","displayColor":"FF9900","displayMaxLineHeight":1.5,"displayCjkSizeRatio":2.0,"displayOptions":[],"displayPadZeros":0.0,"displayType":"ROUTE_COLOR","displayDefaultText":"Ñäk Ħñisòh","doorXMultiplier":0.0,"doorZMultiplier":0.0,"doorAnimationType":"STANDARD","renderFromOpeningDoorTime":0,"renderUntilOpeningDoorTime":0,"renderFromClosingDoorTime":0,"renderUntilClosingDoorTime":0,"flashOffTime":0,"flashOnTime":0},{"names":["head_headcode"],"positionDefinitions":["5356f1b0"],"condition":"NORMAL","renderStage":"EXTERIOR","type":"DISPLAY","displayXPadding":0.0,"displayYPadding":0.0,"displayColorCjk":"FFFFFF","displayColor":"FFFFFF","displayMaxLineHeight":1.5,"displayCjkSizeRatio":2.0,"displayOptions":[],"displayPadZeros":0.0,"displayType":"ROUTE_NUMBER","displayDefaultText":"0000","doorXMultiplier":0.0,"doorZMultiplier":0.0,"doorAnimationType":"STANDARD","renderFromOpeningDoorTime":0,"renderUntilOpeningDoorTime":0,"renderFromClosingDoorTime":0,"renderUntilClosingDoorTime":0,"flashOffTime":0,"flashOnTime":0},{"names":["head_number"],"positionDefinitions":["d16e07c7"],"condition":"NORMAL","renderStage":"EXTERIOR","type":"DISPLAY","displayXPadding":0.0,"displayYPadding":0.0,"displayColorCjk":"FFFFFF","displayColor":"FFFFFF","displayMaxLineHeight":1.5,"displayCjkSizeRatio":2.0,"displayOptions":["SEVEN_SEGMENT"],"displayPadZeros":0.0,"displayType":"DEPARTURE_INDEX","displayDefaultText":"000","doorXMultiplier":0.0,"doorZMultiplier":0.0,"doorAnimationType":"STANDARD","renderFromOpeningDoorTime":0,"renderUntilOpeningDoorTime":0,"renderFromClosingDoorTime":0,"renderUntilClosingDoorTime":0,"flashOffTime":0,"flashOnTime":0},{"names":["int_light"],"positionDefinitions":["98cd32d5"],"condition":"NORMAL","renderStage":"LIGHT","type":"NORMAL","displayXPadding":0.0,"displayYPadding":0.0,"displayColorCjk":"FF9900","displayColor":"FF9900","displayMaxLineHeight":1.5,"displayCjkSizeRatio":2.0,"displayOptions":[],"displayPadZeros":0.0,"displayType":"DESTINATION","displayDefaultText":"Ñäk Ħñisòh","doorXMultiplier":0.0,"doorZMultiplier":0.0,"doorAnimationType":"STANDARD","renderFromOpeningDoorTime":0,"renderUntilOpeningDoorTime":0,"renderFromClosingDoorTime":0,"renderUntilClosingDoorTime":0,"flashOffTime":0,"flashOnTime":0}],"modelYOffset":1.0,"gangwayInnerSideResource":"mtr:textures/gangway/sp1900_side.png","gangwayInnerTopResource":"mtr:textures/gangway/sp1900_roof.png","gangwayInnerBottomResource":"mtr:textures/gangway/sp1900_floor.png","gangwayOuterSideResource":"mtr:textures/gangway/sp1900_exterior.png","gangwayOuterTopResource":"mtr:textures/gangway/sp1900_exterior.png","gangwayOuterBottomResource":"mtr:textures/gangway/sp1900_exterior.png","gangwayWidth":1.5,"gangwayHeight":2.25,"gangwayYOffset":1.0,"gangwayZOffset":0.5,"barrierInnerSideResource":"","barrierInnerTopResource":"","barrierInnerBottomResource":"","barrierOuterSideResource":"","barrierOuterTopResource":"","barrierOuterBottomResource":"","barrierWidth":2.25,"barrierHeight":1.0,"barrierYOffset":1.25,"barrierZOffset":0.25}