{"parts":[{"names":["Intlight"],"positionDefinitions":["e521ae5"],"condition":"NORMAL","renderStage":"LIGHT","type":"NORMAL","displayXPadding":0.0,"displayYPadding":0.0,"displayColorCjk":"","displayColor":"","displayMaxLineHeight":0.0,"displayCjkSizeRatio":0.0,"displayOptions":[],"displayPadZeros":0.0,"displayType":"DESTINATION","displayDefaultText":"","doorXMultiplier":0.0,"doorZMultiplier":0.0,"doorAnimationType":"R179","renderFromOpeningDoorTime":0,"renderUntilOpeningDoorTime":0,"renderFromClosingDoorTime":0,"renderUntilClosingDoorTime":0,"flashOffTime":0,"flashOnTime":0},{"names":["Interior"],"positionDefinitions":["bbc4eb32"],"condition":"NORMAL","renderStage":"INTERIOR","type":"NORMAL","displayXPadding":0.0,"displayYPadding":0.0,"displayColorCjk":"","displayColor":"","displayMaxLineHeight":0.0,"displayCjkSizeRatio":0.0,"displayOptions":[],"displayPadZeros":0.0,"displayType":"DESTINATION","displayDefaultText":"","doorXMultiplier":0.0,"doorZMultiplier":0.0,"doorAnimationType":"R179","renderFromOpeningDoorTime":0,"renderUntilOpeningDoorTime":0,"renderFromClosingDoorTime":0,"renderUntilClosingDoorTime":0,"flashOffTime":0,"flashOnTime":0},{"names":["Door_right_ext"],"positionDefinitions":["9cdd4b5f"],"condition":"NORMAL","renderStage":"EXTERIOR","type":"NORMAL","displayXPadding":0.0,"displayYPadding":0.0,"displayColorCjk":"","displayColor":"","displayMaxLineHeight":0.0,"displayCjkSizeRatio":0.0,"displayOptions":[],"displayPadZeros":0.0,"displayType":"DESTINATION","displayDefaultText":"","doorXMultiplier":-1.0,"doorZMultiplier":-17.0,"doorAnimationType":"R179","renderFromOpeningDoorTime":0,"renderUntilOpeningDoorTime":0,"renderFromClosingDoorTime":0,"renderUntilClosingDoorTime":0,"flashOffTime":0,"flashOnTime":0},{"names":["Door_left_ext"],"positionDefinitions":["d91a634c"],"condition":"NORMAL","renderStage":"EXTERIOR","type":"NORMAL","displayXPadding":0.0,"displayYPadding":0.0,"displayColorCjk":"","displayColor":"","displayMaxLineHeight":0.0,"displayCjkSizeRatio":0.0,"displayOptions":[],"displayPadZeros":0.0,"displayType":"DESTINATION","displayDefaultText":"","doorXMultiplier":-1.0,"doorZMultiplier":17.0,"doorAnimationType":"R179","renderFromOpeningDoorTime":0,"renderUntilOpeningDoorTime":0,"renderFromClosingDoorTime":0,"renderUntilClosingDoorTime":0,"flashOffTime":0,"flashOnTime":0},{"names":["Door_right_ext"],"positionDefinitions":["a65198ad"],"condition":"NORMAL","renderStage":"EXTERIOR","type":"NORMAL","displayXPadding":0.0,"displayYPadding":0.0,"displayColorCjk":"","displayColor":"","displayMaxLineHeight":0.0,"displayCjkSizeRatio":0.0,"displayOptions":[],"displayPadZeros":0.0,"displayType":"DESTINATION","displayDefaultText":"","doorXMultiplier":-1.0,"doorZMultiplier":-17.0,"doorAnimationType":"R179","renderFromOpeningDoorTime":0,"renderUntilOpeningDoorTime":0,"renderFromClosingDoorTime":0,"renderUntilClosingDoorTime":0,"flashOffTime":0,"flashOnTime":0},{"names":["Door_left_ext"],"positionDefinitions":["41b7f856"],"condition":"NORMAL","renderStage":"EXTERIOR","type":"NORMAL","displayXPadding":0.0,"displayYPadding":0.0,"displayColorCjk":"","displayColor":"","displayMaxLineHeight":0.0,"displayCjkSizeRatio":0.0,"displayOptions":[],"displayPadZeros":0.0,"displayType":"DESTINATION","displayDefaultText":"","doorXMultiplier":-1.0,"doorZMultiplier":17.0,"doorAnimationType":"R179","renderFromOpeningDoorTime":0,"renderUntilOpeningDoorTime":0,"renderFromClosingDoorTime":0,"renderUntilClosingDoorTime":0,"flashOffTime":0,"flashOnTime":0},{"names":["Exterior"],"positionDefinitions":["afc58ae"],"condition":"NORMAL","renderStage":"EXTERIOR","type":"NORMAL","displayXPadding":0.0,"displayYPadding":0.0,"displayColorCjk":"","displayColor":"","displayMaxLineHeight":0.0,"displayCjkSizeRatio":0.0,"displayOptions":[],"displayPadZeros":0.0,"displayType":"DESTINATION","displayDefaultText":"","doorXMultiplier":0.0,"doorZMultiplier":0.0,"doorAnimationType":"R179","renderFromOpeningDoorTime":0,"renderUntilOpeningDoorTime":0,"renderFromClosingDoorTime":0,"renderUntilClosingDoorTime":0,"flashOffTime":0,"flashOnTime":0},{"names":["Wheels"],"positionDefinitions":["d61d6717"],"condition":"NORMAL","renderStage":"EXTERIOR","type":"NORMAL","displayXPadding":0.0,"displayYPadding":0.0,"displayColorCjk":"","displayColor":"","displayMaxLineHeight":0.0,"displayCjkSizeRatio":0.0,"displayOptions":[],"displayPadZeros":0.0,"displayType":"DESTINATION","displayDefaultText":"","doorXMultiplier":0.0,"doorZMultiplier":0.0,"doorAnimationType":"R179","renderFromOpeningDoorTime":0,"renderUntilOpeningDoorTime":0,"renderFromClosingDoorTime":0,"renderUntilClosingDoorTime":0,"flashOffTime":0,"flashOnTime":0},{"names":["R"],"positionDefinitions":["ff3261d"],"condition":"ON_ROUTE_FORWARDS","renderStage":"LIGHT","type":"NORMAL","displayXPadding":0.0,"displayYPadding":0.0,"displayColorCjk":"","displayColor":"","displayMaxLineHeight":0.0,"displayCjkSizeRatio":0.0,"displayOptions":[],"displayPadZeros":0.0,"displayType":"DESTINATION","displayDefaultText":"","doorXMultiplier":0.0,"doorZMultiplier":0.0,"doorAnimationType":"R179","renderFromOpeningDoorTime":0,"renderUntilOpeningDoorTime":0,"renderFromClosingDoorTime":0,"renderUntilClosingDoorTime":0,"flashOffTime":0,"flashOnTime":0},{"names":["F"],"positionDefinitions":["235c3dcb"],"condition":"ON_ROUTE_BACKWARDS","renderStage":"LIGHT","type":"NORMAL","displayXPadding":0.0,"displayYPadding":0.0,"displayColorCjk":"","displayColor":"","displayMaxLineHeight":0.0,"displayCjkSizeRatio":0.0,"displayOptions":[],"displayPadZeros":0.0,"displayType":"DESTINATION","displayDefaultText":"","doorXMultiplier":0.0,"doorZMultiplier":0.0,"doorAnimationType":"R179","renderFromOpeningDoorTime":0,"renderUntilOpeningDoorTime":0,"renderFromClosingDoorTime":0,"renderUntilClosingDoorTime":0,"flashOffTime":0,"flashOnTime":0},{"names":["DVDisplayUI_F"],"positionDefinitions":["75ff5f27"],"condition":"ON_ROUTE_FORWARDS","renderStage":"LIGHT","type":"NORMAL","displayXPadding":0.0,"displayYPadding":0.0,"displayColorCjk":"","displayColor":"","displayMaxLineHeight":0.0,"displayCjkSizeRatio":0.0,"displayOptions":[],"displayPadZeros":0.0,"displayType":"DESTINATION","displayDefaultText":"","doorXMultiplier":0.0,"doorZMultiplier":0.0,"doorAnimationType":"R179","renderFromOpeningDoorTime":0,"renderUntilOpeningDoorTime":0,"renderFromClosingDoorTime":0,"renderUntilClosingDoorTime":0,"flashOffTime":0,"flashOnTime":0},{"names":["DVDisplayUI_R"],"positionDefinitions":["7fcf0eb2"],"condition":"ON_ROUTE_BACKWARDS","renderStage":"LIGHT","type":"NORMAL","displayXPadding":0.0,"displayYPadding":0.0,"displayColorCjk":"","displayColor":"","displayMaxLineHeight":0.0,"displayCjkSizeRatio":0.0,"displayOptions":[],"displayPadZeros":0.0,"displayType":"DESTINATION","displayDefaultText":"","doorXMultiplier":0.0,"doorZMultiplier":0.0,"doorAnimationType":"R179","renderFromOpeningDoorTime":0,"renderUntilOpeningDoorTime":0,"renderFromClosingDoorTime":0,"renderUntilClosingDoorTime":0,"flashOffTime":0,"flashOnTime":0},{"names":["DVDisplay_NS"],"positionDefinitions":["3523e360"],"condition":"NORMAL","renderStage":"EXTERIOR","type":"DISPLAY","displayXPadding":0.0,"displayYPadding":0.0,"displayColorCjk":"FF","displayColor":"FF","displayMaxLineHeight":0.0,"displayCjkSizeRatio":0.0,"displayOptions":["SINGLE_LINE"],"displayPadZeros":0.0,"displayType":"NEXT_STATION_MTR","displayDefaultText":"","doorXMultiplier":0.0,"doorZMultiplier":0.0,"doorAnimationType":"R179","renderFromOpeningDoorTime":0,"renderUntilOpeningDoorTime":0,"renderFromClosingDoorTime":0,"renderUntilClosingDoorTime":0,"flashOffTime":0,"flashOnTime":0},{"names":["DVDisplayUI_F"],"positionDefinitions":["26fc2725"],"condition":"ON_ROUTE_BACKWARDS","renderStage":"LIGHT","type":"NORMAL","displayXPadding":0.0,"displayYPadding":0.0,"displayColorCjk":"","displayColor":"","displayMaxLineHeight":0.0,"displayCjkSizeRatio":0.0,"displayOptions":[],"displayPadZeros":0.0,"displayType":"DESTINATION","displayDefaultText":"","doorXMultiplier":0.0,"doorZMultiplier":0.0,"doorAnimationType":"R179","renderFromOpeningDoorTime":0,"renderUntilOpeningDoorTime":0,"renderFromClosingDoorTime":0,"renderUntilClosingDoorTime":0,"flashOffTime":0,"flashOnTime":0},{"names":["DVDisplayUI_R"],"positionDefinitions":["4fbb5352"],"condition":"ON_ROUTE_FORWARDS","renderStage":"LIGHT","type":"NORMAL","displayXPadding":0.0,"displayYPadding":0.0,"displayColorCjk":"","displayColor":"","displayMaxLineHeight":0.0,"displayCjkSizeRatio":0.0,"displayOptions":[],"displayPadZeros":0.0,"displayType":"DESTINATION","displayDefaultText":"","doorXMultiplier":0.0,"doorZMultiplier":0.0,"doorAnimationType":"R179","renderFromOpeningDoorTime":0,"renderUntilOpeningDoorTime":0,"renderFromClosingDoorTime":0,"renderUntilClosingDoorTime":0,"flashOffTime":0,"flashOnTime":0},{"names":["DVDisplay_NS"],"positionDefinitions":["d4212a4f"],"condition":"NORMAL","renderStage":"EXTERIOR","type":"DISPLAY","displayXPadding":0.0,"displayYPadding":0.0,"displayColorCjk":"FF","displayColor":"FF","displayMaxLineHeight":0.0,"displayCjkSizeRatio":0.0,"displayOptions":["SINGLE_LINE"],"displayPadZeros":0.0,"displayType":"NEXT_STATION_MTR","displayDefaultText":"","doorXMultiplier":0.0,"doorZMultiplier":0.0,"doorAnimationType":"R179","renderFromOpeningDoorTime":0,"renderUntilOpeningDoorTime":0,"renderFromClosingDoorTime":0,"renderUntilClosingDoorTime":0,"flashOffTime":0,"flashOnTime":0},{"names":["DVDisplayUI_F"],"positionDefinitions":["36e17964"],"condition":"ON_ROUTE_FORWARDS","renderStage":"LIGHT","type":"NORMAL","displayXPadding":0.0,"displayYPadding":0.0,"displayColorCjk":"","displayColor":"","displayMaxLineHeight":0.0,"displayCjkSizeRatio":0.0,"displayOptions":[],"displayPadZeros":0.0,"displayType":"DESTINATION","displayDefaultText":"","doorXMultiplier":0.0,"doorZMultiplier":0.0,"doorAnimationType":"R179","renderFromOpeningDoorTime":0,"renderUntilOpeningDoorTime":0,"renderFromClosingDoorTime":0,"renderUntilClosingDoorTime":0,"flashOffTime":0,"flashOnTime":0},{"names":["DVDisplayUI_R"],"positionDefinitions":["95ed9f75"],"condition":"ON_ROUTE_BACKWARDS","renderStage":"LIGHT","type":"NORMAL","displayXPadding":0.0,"displayYPadding":0.0,"displayColorCjk":"","displayColor":"","displayMaxLineHeight":0.0,"displayCjkSizeRatio":0.0,"displayOptions":[],"displayPadZeros":0.0,"displayType":"DESTINATION","displayDefaultText":"","doorXMultiplier":0.0,"doorZMultiplier":0.0,"doorAnimationType":"R179","renderFromOpeningDoorTime":0,"renderUntilOpeningDoorTime":0,"renderFromClosingDoorTime":0,"renderUntilClosingDoorTime":0,"flashOffTime":0,"flashOnTime":0},{"names":["DVDisplay_NS"],"positionDefinitions":["b2008514"],"condition":"NORMAL","renderStage":"EXTERIOR","type":"DISPLAY","displayXPadding":0.0,"displayYPadding":0.0,"displayColorCjk":"FF","displayColor":"FF","displayMaxLineHeight":0.0,"displayCjkSizeRatio":0.0,"displayOptions":["SINGLE_LINE"],"displayPadZeros":0.0,"displayType":"NEXT_STATION_MTR","displayDefaultText":"","doorXMultiplier":0.0,"doorZMultiplier":0.0,"doorAnimationType":"R179","renderFromOpeningDoorTime":0,"renderUntilOpeningDoorTime":0,"renderFromClosingDoorTime":0,"renderUntilClosingDoorTime":0,"flashOffTime":0,"flashOnTime":0},{"names":["DVDisplayUI_F"],"positionDefinitions":["fb336781"],"condition":"ON_ROUTE_BACKWARDS","renderStage":"LIGHT","type":"NORMAL","displayXPadding":0.0,"displayYPadding":0.0,"displayColorCjk":"","displayColor":"","displayMaxLineHeight":0.0,"displayCjkSizeRatio":0.0,"displayOptions":[],"displayPadZeros":0.0,"displayType":"DESTINATION","displayDefaultText":"","doorXMultiplier":0.0,"doorZMultiplier":0.0,"doorAnimationType":"R179","renderFromOpeningDoorTime":0,"renderUntilOpeningDoorTime":0,"renderFromClosingDoorTime":0,"renderUntilClosingDoorTime":0,"flashOffTime":0,"flashOnTime":0},{"names":["DVDisplayUI_R"],"positionDefinitions":["fa63b3b7"],"condition":"ON_ROUTE_FORWARDS","renderStage":"LIGHT","type":"NORMAL","displayXPadding":0.0,"displayYPadding":0.0,"displayColorCjk":"","displayColor":"","displayMaxLineHeight":0.0,"displayCjkSizeRatio":0.0,"displayOptions":[],"displayPadZeros":0.0,"displayType":"DESTINATION","displayDefaultText":"","doorXMultiplier":0.0,"doorZMultiplier":0.0,"doorAnimationType":"R179","renderFromOpeningDoorTime":0,"renderUntilOpeningDoorTime":0,"renderFromClosingDoorTime":0,"renderUntilClosingDoorTime":0,"flashOffTime":0,"flashOnTime":0},{"names":["DVDisplay_NS"],"positionDefinitions":["2da2fbd"],"condition":"NORMAL","renderStage":"EXTERIOR","type":"DISPLAY","displayXPadding":0.0,"displayYPadding":0.0,"displayColorCjk":"FF","displayColor":"FF","displayMaxLineHeight":0.0,"displayCjkSizeRatio":0.0,"displayOptions":["SINGLE_LINE"],"displayPadZeros":0.0,"displayType":"NEXT_STATION_MTR","displayDefaultText":"","doorXMultiplier":0.0,"doorZMultiplier":0.0,"doorAnimationType":"R179","renderFromOpeningDoorTime":0,"renderUntilOpeningDoorTime":0,"renderFromClosingDoorTime":0,"renderUntilClosingDoorTime":0,"flashOffTime":0,"flashOnTime":0},{"names":["AirportVariant"],"positionDefinitions":["813737fe"],"condition":"NORMAL","renderStage":"INTERIOR","type":"NORMAL","displayXPadding":0.0,"displayYPadding":0.0,"displayColorCjk":"","displayColor":"","displayMaxLineHeight":0.0,"displayCjkSizeRatio":0.0,"displayOptions":[],"displayPadZeros":0.0,"displayType":"DESTINATION","displayDefaultText":"","doorXMultiplier":0.0,"doorZMultiplier":0.0,"doorAnimationType":"R179","renderFromOpeningDoorTime":0,"renderUntilOpeningDoorTime":0,"renderFromClosingDoorTime":0,"renderUntilClosingDoorTime":0,"flashOffTime":0,"flashOnTime":0},{"names":["Door_right_int"],"positionDefinitions":["16075569"],"condition":"NORMAL","renderStage":"INTERIOR","type":"NORMAL","displayXPadding":0.0,"displayYPadding":0.0,"displayColorCjk":"FF9900","displayColor":"FF9900","displayMaxLineHeight":1.5,"displayCjkSizeRatio":2.0,"displayOptions":[],"displayPadZeros":0.0,"displayType":"DESTINATION","displayDefaultText":"Not In Service","doorXMultiplier":0.0,"doorZMultiplier":-17.0,"doorAnimationType":"R179","renderFromOpeningDoorTime":0,"renderUntilOpeningDoorTime":0,"renderFromClosingDoorTime":0,"renderUntilClosingDoorTime":0,"flashOffTime":0,"flashOnTime":0},{"names":["Door_left_int"],"positionDefinitions":["e5404b9a"],"condition":"NORMAL","renderStage":"INTERIOR","type":"NORMAL","displayXPadding":0.0,"displayYPadding":0.0,"displayColorCjk":"FF9900","displayColor":"FF9900","displayMaxLineHeight":1.5,"displayCjkSizeRatio":2.0,"displayOptions":[],"displayPadZeros":0.0,"displayType":"DESTINATION","displayDefaultText":"Not In Service","doorXMultiplier":0.0,"doorZMultiplier":17.0,"doorAnimationType":"R179","renderFromOpeningDoorTime":0,"renderUntilOpeningDoorTime":0,"renderFromClosingDoorTime":0,"renderUntilClosingDoorTime":0,"flashOffTime":0,"flashOnTime":0},{"names":["Door_right_int"],"positionDefinitions":["70940f5b"],"condition":"NORMAL","renderStage":"INTERIOR","type":"NORMAL","displayXPadding":0.0,"displayYPadding":0.0,"displayColorCjk":"FF9900","displayColor":"FF9900","displayMaxLineHeight":1.5,"displayCjkSizeRatio":2.0,"displayOptions":[],"displayPadZeros":0.0,"displayType":"DESTINATION","displayDefaultText":"Not In Service","doorXMultiplier":0.0,"doorZMultiplier":-17.0,"doorAnimationType":"R179","renderFromOpeningDoorTime":0,"renderUntilOpeningDoorTime":0,"renderFromClosingDoorTime":0,"renderUntilClosingDoorTime":0,"flashOffTime":0,"flashOnTime":0},{"names":["Door_left_int"],"positionDefinitions":["f7f782f2"],"condition":"NORMAL","renderStage":"INTERIOR","type":"NORMAL","displayXPadding":0.0,"displayYPadding":0.0,"displayColorCjk":"FF9900","displayColor":"FF9900","displayMaxLineHeight":1.5,"displayCjkSizeRatio":2.0,"displayOptions":[],"displayPadZeros":0.0,"displayType":"DESTINATION","displayDefaultText":"Not In Service","doorXMultiplier":0.0,"doorZMultiplier":17.0,"doorAnimationType":"R179","renderFromOpeningDoorTime":0,"renderUntilOpeningDoorTime":0,"renderFromClosingDoorTime":0,"renderUntilClosingDoorTime":0,"flashOffTime":0,"flashOnTime":0},{"names":["Door_right_int"],"positionDefinitions":["d33d8830"],"condition":"NORMAL","renderStage":"INTERIOR","type":"NORMAL","displayXPadding":0.0,"displayYPadding":0.0,"displayColorCjk":"FF9900","displayColor":"FF9900","displayMaxLineHeight":1.5,"displayCjkSizeRatio":2.0,"displayOptions":[],"displayPadZeros":0.0,"displayType":"DESTINATION","displayDefaultText":"Not In Service","doorXMultiplier":0.0,"doorZMultiplier":-17.0,"doorAnimationType":"R179","renderFromOpeningDoorTime":0,"renderUntilOpeningDoorTime":0,"renderFromClosingDoorTime":0,"renderUntilClosingDoorTime":0,"flashOffTime":0,"flashOnTime":0},{"names":["Door_left_int"],"positionDefinitions":["de9ff901"],"condition":"NORMAL","renderStage":"INTERIOR","type":"NORMAL","displayXPadding":0.0,"displayYPadding":0.0,"displayColorCjk":"FF9900","displayColor":"FF9900","displayMaxLineHeight":1.5,"displayCjkSizeRatio":2.0,"displayOptions":[],"displayPadZeros":0.0,"displayType":"DESTINATION","displayDefaultText":"Not In Service","doorXMultiplier":0.0,"doorZMultiplier":17.0,"doorAnimationType":"R179","renderFromOpeningDoorTime":0,"renderUntilOpeningDoorTime":0,"renderFromClosingDoorTime":0,"renderUntilClosingDoorTime":0,"flashOffTime":0,"flashOnTime":0},{"names":["Door_right_int"],"positionDefinitions":["485e8d64"],"condition":"NORMAL","renderStage":"INTERIOR","type":"NORMAL","displayXPadding":0.0,"displayYPadding":0.0,"displayColorCjk":"FF9900","displayColor":"FF9900","displayMaxLineHeight":1.5,"displayCjkSizeRatio":2.0,"displayOptions":[],"displayPadZeros":0.0,"displayType":"DESTINATION","displayDefaultText":"Not In Service","doorXMultiplier":0.0,"doorZMultiplier":-17.0,"doorAnimationType":"R179","renderFromOpeningDoorTime":0,"renderUntilOpeningDoorTime":0,"renderFromClosingDoorTime":0,"renderUntilClosingDoorTime":0,"flashOffTime":0,"flashOnTime":0},{"names":["Door_left_int"],"positionDefinitions":["ab4b2303"],"condition":"NORMAL","renderStage":"INTERIOR","type":"NORMAL","displayXPadding":0.0,"displayYPadding":0.0,"displayColorCjk":"FF9900","displayColor":"FF9900","displayMaxLineHeight":1.5,"displayCjkSizeRatio":2.0,"displayOptions":[],"displayPadZeros":0.0,"displayType":"DESTINATION","displayDefaultText":"Not In Service","doorXMultiplier":0.0,"doorZMultiplier":17.0,"doorAnimationType":"R179","renderFromOpeningDoorTime":0,"renderUntilOpeningDoorTime":0,"renderFromClosingDoorTime":0,"renderUntilClosingDoorTime":0,"flashOffTime":0,"flashOnTime":0},{"names":["Door_right_ext1"],"positionDefinitions":["4cc88e5a"],"condition":"NORMAL","renderStage":"EXTERIOR","type":"NORMAL","displayXPadding":0.0,"displayYPadding":0.0,"displayColorCjk":"FF9900","displayColor":"FF9900","displayMaxLineHeight":1.5,"displayCjkSizeRatio":2.0,"displayOptions":[],"displayPadZeros":0.0,"displayType":"DESTINATION","displayDefaultText":"Not In Service","doorXMultiplier":0.0,"doorZMultiplier":-17.0,"doorAnimationType":"R179","renderFromOpeningDoorTime":0,"renderUntilOpeningDoorTime":0,"renderFromClosingDoorTime":0,"renderUntilClosingDoorTime":0,"flashOffTime":0,"flashOnTime":0},{"names":["Door_left_ext1"],"positionDefinitions":["d8c4ff0"],"condition":"NORMAL","renderStage":"EXTERIOR","type":"NORMAL","displayXPadding":0.0,"displayYPadding":0.0,"displayColorCjk":"FF9900","displayColor":"FF9900","displayMaxLineHeight":1.5,"displayCjkSizeRatio":2.0,"displayOptions":[],"displayPadZeros":0.0,"displayType":"DESTINATION","displayDefaultText":"Not In Service","doorXMultiplier":0.0,"doorZMultiplier":17.0,"doorAnimationType":"R179","renderFromOpeningDoorTime":0,"renderUntilOpeningDoorTime":0,"renderFromClosingDoorTime":0,"renderUntilClosingDoorTime":0,"flashOffTime":0,"flashOnTime":0},{"names":["Door_right_ext2"],"positionDefinitions":["b25dd0bd"],"condition":"NORMAL","renderStage":"EXTERIOR","type":"NORMAL","displayXPadding":0.0,"displayYPadding":0.0,"displayColorCjk":"FF9900","displayColor":"FF9900","displayMaxLineHeight":1.5,"displayCjkSizeRatio":2.0,"displayOptions":[],"displayPadZeros":0.0,"displayType":"DESTINATION","displayDefaultText":"Not In Service","doorXMultiplier":0.0,"doorZMultiplier":-17.0,"doorAnimationType":"R179","renderFromOpeningDoorTime":0,"renderUntilOpeningDoorTime":0,"renderFromClosingDoorTime":0,"renderUntilClosingDoorTime":0,"flashOffTime":0,"flashOnTime":0},{"names":["Door_left_ext2"],"positionDefinitions":["4224ee82"],"condition":"NORMAL","renderStage":"EXTERIOR","type":"NORMAL","displayXPadding":0.0,"displayYPadding":0.0,"displayColorCjk":"FF9900","displayColor":"FF9900","displayMaxLineHeight":1.5,"displayCjkSizeRatio":2.0,"displayOptions":[],"displayPadZeros":0.0,"displayType":"DESTINATION","displayDefaultText":"Not In Service","doorXMultiplier":0.0,"doorZMultiplier":17.0,"doorAnimationType":"R179","renderFromOpeningDoorTime":0,"renderUntilOpeningDoorTime":0,"renderFromClosingDoorTime":0,"renderUntilClosingDoorTime":0,"flashOffTime":0,"flashOnTime":0},{"names":["Door_right_ext2"],"positionDefinitions":["ff8519a1"],"condition":"NORMAL","renderStage":"EXTERIOR","type":"NORMAL","displayXPadding":0.0,"displayYPadding":0.0,"displayColorCjk":"FF9900","displayColor":"FF9900","displayMaxLineHeight":1.5,"displayCjkSizeRatio":2.0,"displayOptions":[],"displayPadZeros":0.0,"displayType":"DESTINATION","displayDefaultText":"Not In Service","doorXMultiplier":0.0,"doorZMultiplier":-17.0,"doorAnimationType":"R179","renderFromOpeningDoorTime":0,"renderUntilOpeningDoorTime":0,"renderFromClosingDoorTime":0,"renderUntilClosingDoorTime":0,"flashOffTime":0,"flashOnTime":0},{"names":["Door_left_ext2"],"positionDefinitions":["d368e42c"],"condition":"NORMAL","renderStage":"EXTERIOR","type":"NORMAL","displayXPadding":0.0,"displayYPadding":0.0,"displayColorCjk":"FF9900","displayColor":"FF9900","displayMaxLineHeight":1.5,"displayCjkSizeRatio":2.0,"displayOptions":[],"displayPadZeros":0.0,"displayType":"DESTINATION","displayDefaultText":"Not In Service","doorXMultiplier":0.0,"doorZMultiplier":17.0,"doorAnimationType":"R179","renderFromOpeningDoorTime":0,"renderUntilOpeningDoorTime":0,"renderFromClosingDoorTime":0,"renderUntilClosingDoorTime":0,"flashOffTime":0,"flashOnTime":0},{"names":["Door_right_ext1"],"positionDefinitions":["3e9aa0ca"],"condition":"NORMAL","renderStage":"EXTERIOR","type":"NORMAL","displayXPadding":0.0,"displayYPadding":0.0,"displayColorCjk":"FF9900","displayColor":"FF9900","displayMaxLineHeight":1.5,"displayCjkSizeRatio":2.0,"displayOptions":[],"displayPadZeros":0.0,"displayType":"DESTINATION","displayDefaultText":"Not In Service","doorXMultiplier":0.0,"doorZMultiplier":-17.0,"doorAnimationType":"R179","renderFromOpeningDoorTime":0,"renderUntilOpeningDoorTime":0,"renderFromClosingDoorTime":0,"renderUntilClosingDoorTime":0,"flashOffTime":0,"flashOnTime":0},{"names":["Door_left_ext1"],"positionDefinitions":["8de64ea6"],"condition":"NORMAL","renderStage":"EXTERIOR","type":"NORMAL","displayXPadding":0.0,"displayYPadding":0.0,"displayColorCjk":"FF9900","displayColor":"FF9900","displayMaxLineHeight":1.5,"displayCjkSizeRatio":2.0,"displayOptions":[],"displayPadZeros":0.0,"displayType":"DESTINATION","displayDefaultText":"Not In Service","doorXMultiplier":0.0,"doorZMultiplier":17.0,"doorAnimationType":"R179","renderFromOpeningDoorTime":0,"renderUntilOpeningDoorTime":0,"renderFromClosingDoorTime":0,"renderUntilClosingDoorTime":0,"flashOffTime":0,"flashOnTime":0},{"names":["floor2"],"positionDefinitions":["170e6f46"],"condition":"NORMAL","renderStage":"EXTERIOR","type":"FLOOR","displayXPadding":0.0,"displayYPadding":0.0,"displayColorCjk":"FF9900","displayColor":"FF9900","displayMaxLineHeight":1.5,"displayCjkSizeRatio":2.0,"displayOptions":[],"displayPadZeros":0.0,"displayType":"DESTINATION","displayDefaultText":"Not In Service","doorXMultiplier":0.0,"doorZMultiplier":0.0,"doorAnimationType":"STANDARD","renderFromOpeningDoorTime":0,"renderUntilOpeningDoorTime":0,"renderFromClosingDoorTime":0,"renderUntilClosingDoorTime":0,"flashOffTime":0,"flashOnTime":0},{"names":["doorway"],"positionDefinitions":["c1507001"],"condition":"NORMAL","renderStage":"EXTERIOR","type":"DOORWAY","displayXPadding":0.0,"displayYPadding":0.0,"displayColorCjk":"FF9900","displayColor":"FF9900","displayMaxLineHeight":1.5,"displayCjkSizeRatio":2.0,"displayOptions":[],"displayPadZeros":0.0,"displayType":"DESTINATION","displayDefaultText":"Not In Service","doorXMultiplier":0.0,"doorZMultiplier":0.0,"doorAnimationType":"STANDARD","renderFromOpeningDoorTime":0,"renderUntilOpeningDoorTime":0,"renderFromClosingDoorTime":0,"renderUntilClosingDoorTime":0,"flashOffTime":0,"flashOnTime":0},{"names":["doorway"],"positionDefinitions":["8fb6e06f"],"condition":"NORMAL","renderStage":"EXTERIOR","type":"DOORWAY","displayXPadding":0.0,"displayYPadding":0.0,"displayColorCjk":"FF9900","displayColor":"FF9900","displayMaxLineHeight":1.5,"displayCjkSizeRatio":2.0,"displayOptions":[],"displayPadZeros":0.0,"displayType":"DESTINATION","displayDefaultText":"Not In Service","doorXMultiplier":0.0,"doorZMultiplier":0.0,"doorAnimationType":"STANDARD","renderFromOpeningDoorTime":0,"renderUntilOpeningDoorTime":0,"renderFromClosingDoorTime":0,"renderUntilClosingDoorTime":0,"flashOffTime":0,"flashOnTime":0},{"names":["doorway"],"positionDefinitions":["3fbaef95"],"condition":"NORMAL","renderStage":"EXTERIOR","type":"DOORWAY","displayXPadding":0.0,"displayYPadding":0.0,"displayColorCjk":"FF9900","displayColor":"FF9900","displayMaxLineHeight":1.5,"displayCjkSizeRatio":2.0,"displayOptions":[],"displayPadZeros":0.0,"displayType":"DESTINATION","displayDefaultText":"Not In Service","doorXMultiplier":0.0,"doorZMultiplier":0.0,"doorAnimationType":"STANDARD","renderFromOpeningDoorTime":0,"renderUntilOpeningDoorTime":0,"renderFromClosingDoorTime":0,"renderUntilClosingDoorTime":0,"flashOffTime":0,"flashOnTime":0},{"names":["doorway"],"positionDefinitions":["e9cb67b0"],"condition":"NORMAL","renderStage":"EXTERIOR","type":"DOORWAY","displayXPadding":0.0,"displayYPadding":0.0,"displayColorCjk":"FF9900","displayColor":"FF9900","displayMaxLineHeight":1.5,"displayCjkSizeRatio":2.0,"displayOptions":[],"displayPadZeros":0.0,"displayType":"DESTINATION","displayDefaultText":"Not In Service","doorXMultiplier":0.0,"doorZMultiplier":0.0,"doorAnimationType":"STANDARD","renderFromOpeningDoorTime":0,"renderUntilOpeningDoorTime":0,"renderFromClosingDoorTime":0,"renderUntilClosingDoorTime":0,"flashOffTime":0,"flashOnTime":0}],"modelYOffset":1.0,"gangwayInnerSideResource":"mtr:apm300r/apm300r_denver_connector_side.png","gangwayInnerTopResource":"mtr:apm300r/apm300r_denver_connector_roof.png","gangwayInnerBottomResource":"mtr:apm300r/apm300r_denver_connector_floor.png","gangwayOuterSideResource":"mtr:apm300r/apm300r_denver_connector_exterior.png","gangwayOuterTopResource":"mtr:apm300r/apm300r_denver_connector_exterior.png","gangwayOuterBottomResource":"mtr:apm300r/apm300r_denver_connector_exterior.png","gangwayWidth":1.5,"gangwayHeight":2.25,"gangwayYOffset":1.0,"gangwayZOffset":0.5,"barrierInnerSideResource":"_exterior.png","barrierInnerTopResource":"","barrierInnerBottomResource":"","barrierOuterSideResource":"_exterior.png","barrierOuterTopResource":"","barrierOuterBottomResource":"","barrierWidth":2.25,"barrierHeight":1.0,"barrierYOffset":1.25,"barrierZOffset":0.25}