{"positionDefinitions":[{"name":"2cc04abf","positions":[{"x":0.0,"y":0.0,"z":0.0}],"positionsFlipped":[]},{"name":"38f75acb","positions":[{"x":0.0,"y":0.0,"z":0.0}],"positionsFlipped":[]},{"name":"434cc7f7","positions":[{"x":0.0,"y":0.0,"z":0.0}],"positionsFlipped":[]},{"name":"ec227ac","positions":[{"x":0.0,"y":0.0,"z":0.0}],"positionsFlipped":[]},{"name":"519003ef","positions":[{"x":0.0,"y":0.0,"z":0.0}],"positionsFlipped":[]},{"name":"821bde17","positions":[{"x":0.0,"y":0.0,"z":0.0}],"positionsFlipped":[]},{"name":"302ac26f","positions":[{"x":0.0,"y":0.0,"z":0.0}],"positionsFlipped":[]},{"name":"863aff84","positions":[{"x":0.0,"y":0.0,"z":0.0}],"positionsFlipped":[]},{"name":"886b2ef1","positions":[{"x":0.0,"y":0.0,"z":0.0}],"positionsFlipped":[]},{"name":"48acd341","positions":[{"x":0.0,"y":0.0,"z":0.0}],"positionsFlipped":[]},{"name":"a334ae29","positions":[{"x":0.0,"y":0.0,"z":0.0}],"positionsFlipped":[]},{"name":"68cd681","positions":[{"x":0.0,"y":0.0,"z":0.0}],"positionsFlipped":[]},{"name":"94006c3d","positions":[{"x":0.0,"y":0.0,"z":0.0}],"positionsFlipped":[]},{"name":"b35a5190","positions":[{"x":0.0,"y":0.0,"z":0.0}],"positionsFlipped":[]},{"name":"9bb9cad7","positions":[{"x":0.0,"y":0.0,"z":0.0}],"positionsFlipped":[]},{"name":"77edd4d0","positions":[{"x":0.0,"y":0.0,"z":0.0}],"positionsFlipped":[]},{"name":"be3ef9cb","positions":[{"x":0.0,"y":0.0,"z":0.0}],"positionsFlipped":[]},{"name":"bf505410","positions":[{"x":0.0,"y":0.0,"z":0.0}],"positionsFlipped":[]}]}